{"+NPhLrgPtjtjixDmMBuEog==":"63259277-2323018951088013-6095555321789415424-o-1984x1104.jpg","Xf72dEPvN4WllVlwFoc4nA==":"1562492176976_routes-1405x857.jpg","kahCPZsl98evAKhEf74O+Q==":"hong-kong1-560x336.jpg","ofWhAcD31SFdbidQ5WLy7A==":"bangkok-560x336.jpg","ASrH9YcUvQ1yBk/r/bAKXw==":"kanchanaburi-560x336.jpg","yZxOrUA+N1xfX2r38VvqZA==":"phraya-nakhon-cave-560x336.jpg","tIi//RjdVR+Yp7OPIE+2hA==":"koh-tao-2-560x336.jpg","P1nwZtppEucOXBnKr+ymgQ==":"khaosoknationalpark-2-560x335.jpg","Xz2bbGkDUk1Za8mAzquf2Q==":"20190628-132915-1280x719.jpg","oF1BiaEAQxh6GxNBimEAEw==":"20190627-104600-1280x720.jpg","cE6dV8A2Wwjvksa32hHuOg==":"20190702-115507-1280x720.jpg","URYPtNvF/YsUrsShDEf1Fg==":"20190628-105239-1280x720.jpg"}